test/__init__.py
test/torch_wild.py
torch_wild-0.1.dist-info/METADATA
torch_wild-0.1.dist-info/WHEEL
torch_wild-0.1.dist-info/top_level.txt
torch_wild-0.1.dist-info/RECORD
